DbObject.py
Errors.py
Schema.py
db_schema_tshonq-0.0.3.dist-info/METADATA
db_schema_tshonq-0.0.3.dist-info/WHEEL
db_schema_tshonq-0.0.3.dist-info/top_level.txt
db_schema_tshonq-0.0.3.dist-info/RECORD
