Metadata-Version: 2.1
Name: db_schema_tshonq
Version: 0.0.3
Summary: A small schema package for database uses.
Author-email: Akshit Shubham <akshit@1471bl.onmicrosoft.com>
Classifier: Programming Language :: Python :: 3
Classifier: License :: OSI Approved :: MIT License
Classifier: Operating System :: OS Independent
Requires-Python: >=3.8
